settle/__init__.py
settle/api.py
settle/auth.py
settle/data_details.py
settle/settings.py
settle/transfers.py
settle.africa-0.1.0.dist-info/METADATA
settle.africa-0.1.0.dist-info/WHEEL
settle.africa-0.1.0.dist-info/top_level.txt
settle.africa-0.1.0.dist-info/RECORD
